{
  "syntax_13773": {
    "id": 13773,
    "creator": "tgbhy",
    "title": "Player Jobs",
    "description": "Gets __all the jobs__ of a __player__.",
    "syntax_pattern": "[all] job[s] (of|from) %player%",
    "compatible_addon_version": "1.0.2",
    "compatible_minecraft_version": null,
    "syntax_type": "expression",
    "required_plugins": [
      {
        "name": "JobsReborn",
        "link": ""
      }
    ],
    "addon": "JobsSK",
    "type_usage": null,
    "return_type": "Job",
    "event_values": null,
    "event_cancellable": false,
    "link": "http://skripthub.net/docs/?id=13773",
    "created_at": "2025-06-29T11:40:13.664414Z",
    "updated_at": "2025-06-29T11:40:13.664428Z",
    "entries": null,
    "keywords": null,
    "mark_as_removed": false,
    "removed_since": null,
    "guide": {
      "en": [
        "Gets __all the jobs__ of a __player__."
      ],
      "ko": [
        "[JOBSSK] 한국어 가이드 번역 대기 중"
      ]
    }
  },
  "syntax_13768": {
    "id": 13768,
    "creator": "tgbhy",
    "title": "On Job Join",
    "description": "Called when a player joins a __JobsReborn__ job.",
    "syntax_pattern": "player join [(a|the)] job [[(with name|named) ]%-string%]",
    "compatible_addon_version": "1.0.2",
    "compatible_minecraft_version": null,
    "syntax_type": "event",
    "required_plugins": [
      {
        "name": "JobsReborn",
        "link": ""
      }
    ],
    "addon": "JobsSK",
    "type_usage": null,
    "return_type": null,
    "event_values": "event-job, event-player",
    "event_cancellable": false,
    "link": "http://skripthub.net/docs/?id=13768",
    "created_at": "2025-06-29T11:19:23.353736Z",
    "updated_at": "2025-06-29T11:19:23.353754Z",
    "entries": null,
    "keywords": null,
    "mark_as_removed": false,
    "removed_since": null,
    "guide": {
      "en": [
        "Called when a player joins a __JobsReborn__ job."
      ],
      "ko": [
        "[JOBSSK] 한국어 가이드 번역 대기 중"
      ]
    }
  },
  "syntax_13769": {
    "id": 13769,
    "creator": "tgbhy",
    "title": "Job",
    "description": "Gets the created with JobsReborn job based on its __id__ or __name__.",
    "syntax_pattern": "[the] job [(named|with name)] %string%",
    "compatible_addon_version": "1.0.2",
    "compatible_minecraft_version": null,
    "syntax_type": "expression",
    "required_plugins": [
      {
        "name": "JobsReborn",
        "link": ""
      }
    ],
    "addon": "JobsSK",
    "type_usage": null,
    "return_type": "Job",
    "event_values": null,
    "event_cancellable": false,
    "link": "http://skripthub.net/docs/?id=13769",
    "created_at": "2025-06-29T11:22:24.094165Z",
    "updated_at": "2025-06-29T11:22:24.094182Z",
    "entries": null,
    "keywords": null,
    "mark_as_removed": false,
    "removed_since": null,
    "guide": {
      "en": [
        "Gets the created with JobsReborn job based on its __id__ or __name__."
      ],
      "ko": [
        "[JOBSSK] 한국어 가이드 번역 대기 중"
      ]
    }
  },
  "syntax_13774": {
    "id": 13774,
    "creator": "tgbhy",
    "title": "Player Job Levels",
    "description": "Gets __levels__ of a __player__ for a created with JobsReborn job.",
    "syntax_pattern": "(level[s]|lvl) (of|from) %-job% of %-player%",
    "compatible_addon_version": "1.0.2",
    "compatible_minecraft_version": null,
    "syntax_type": "expression",
    "required_plugins": [
      {
        "name": "JobsReborn",
        "link": ""
      }
    ],
    "addon": "JobsSK",
    "type_usage": null,
    "return_type": "Integer",
    "event_values": null,
    "event_cancellable": false,
    "link": "http://skripthub.net/docs/?id=13774",
    "created_at": "2025-06-29T11:42:24.844199Z",
    "updated_at": "2025-06-29T11:42:24.844216Z",
    "entries": null,
    "keywords": null,
    "mark_as_removed": false,
    "removed_since": null,
    "guide": {
      "en": [
        "Gets __levels__ of a __player__ for a created with JobsReborn job."
      ],
      "ko": [
        "[JOBSSK] 한국어 가이드 번역 대기 중"
      ]
    }
  },
  "syntax_13770": {
    "id": 13770,
    "creator": "tgbhy",
    "title": "Job DisplayName",
    "description": "Gets the __displayname__ of a created with JobsReborn job.",
    "syntax_pattern": "%job%['s] display[name]",
    "compatible_addon_version": "1.0.2",
    "compatible_minecraft_version": null,
    "syntax_type": "expression",
    "required_plugins": [
      {
        "name": "JobsReborn",
        "link": ""
      }
    ],
    "addon": "JobsSK",
    "type_usage": null,
    "return_type": "String",
    "event_values": null,
    "event_cancellable": false,
    "link": "http://skripthub.net/docs/?id=13770",
    "created_at": "2025-06-29T11:24:29.868328Z",
    "updated_at": "2025-06-29T11:24:29.868348Z",
    "entries": null,
    "keywords": null,
    "mark_as_removed": false,
    "removed_since": null,
    "guide": {
      "en": [
        "Gets the __displayname__ of a created with JobsReborn job."
      ],
      "ko": [
        "[JOBSSK] 한국어 가이드 번역 대기 중"
      ]
    }
  },
  "syntax_13775": {
    "id": 13775,
    "creator": "tgbhy",
    "title": "Player Job XP",
    "description": "Gets __xp__ of a __player__ in a created with JobsReborn job.",
    "syntax_pattern": "([e]xp) (of|from) %job% of %player%",
    "compatible_addon_version": "1.0.2",
    "compatible_minecraft_version": null,
    "syntax_type": "expression",
    "required_plugins": [
      {
        "name": "JobsReborn",
        "link": ""
      }
    ],
    "addon": "JobsSK",
    "type_usage": null,
    "return_type": "Double",
    "event_values": null,
    "event_cancellable": false,
    "link": "http://skripthub.net/docs/?id=13775",
    "created_at": "2025-06-29T11:43:55.522346Z",
    "updated_at": "2025-06-29T11:43:55.522363Z",
    "entries": null,
    "keywords": null,
    "mark_as_removed": false,
    "removed_since": null,
    "guide": {
      "en": [
        "Gets __xp__ of a __player__ in a created with JobsReborn job."
      ],
      "ko": [
        "[JOBSSK] 한국어 가이드 번역 대기 중"
      ]
    }
  },
  "syntax_13771": {
    "id": 13771,
    "creator": "tgbhy",
    "title": "Job ID",
    "description": "Gets the __id__ of a created with JobsReborn job.",
    "syntax_pattern": "%job%['s] id",
    "compatible_addon_version": "1.0.2",
    "compatible_minecraft_version": null,
    "syntax_type": "expression",
    "required_plugins": [
      {
        "name": "JobsReborn",
        "link": ""
      }
    ],
    "addon": "JobsSK",
    "type_usage": null,
    "return_type": "Integer",
    "event_values": null,
    "event_cancellable": false,
    "link": "http://skripthub.net/docs/?id=13771",
    "created_at": "2025-06-29T11:26:30.982811Z",
    "updated_at": "2025-06-29T11:26:30.982831Z",
    "entries": null,
    "keywords": null,
    "mark_as_removed": false,
    "removed_since": null,
    "guide": {
      "en": [
        "Gets the __id__ of a created with JobsReborn job."
      ],
      "ko": [
        "[JOBSSK] 한국어 가이드 번역 대기 중"
      ]
    }
  },
  "syntax_13766": {
    "id": 13766,
    "creator": "tgbhy",
    "title": "Jobs",
    "description": "Represents a Job created with __JobsReborn__ plugin.",
    "syntax_pattern": "job[s]",
    "compatible_addon_version": "1.0.2",
    "compatible_minecraft_version": null,
    "syntax_type": "type",
    "required_plugins": [
      {
        "name": "JobsReborn",
        "link": ""
      }
    ],
    "addon": "JobsSK",
    "type_usage": null,
    "return_type": null,
    "event_values": null,
    "event_cancellable": false,
    "link": "http://skripthub.net/docs/?id=13766",
    "created_at": "2025-06-29T11:02:18.724659Z",
    "updated_at": "2025-06-29T11:02:18.724680Z",
    "entries": null,
    "keywords": null,
    "mark_as_removed": false,
    "removed_since": null,
    "guide": {
      "en": [
        "Represents a Job created with __JobsReborn__ plugin."
      ],
      "ko": [
        "[JOBSSK] 한국어 가이드 번역 대기 중"
      ]
    }
  },
  "syntax_13772": {
    "id": 13772,
    "creator": "tgbhy",
    "title": "Job Name",
    "description": "Gets the __name__ of a created with JobsReborn job.",
    "syntax_pattern": "%job%['s] jobname",
    "compatible_addon_version": "1.0.2",
    "compatible_minecraft_version": null,
    "syntax_type": "expression",
    "required_plugins": [
      {
        "name": "JobsReborn",
        "link": ""
      }
    ],
    "addon": "JobsSK",
    "type_usage": null,
    "return_type": "String",
    "event_values": null,
    "event_cancellable": false,
    "link": "http://skripthub.net/docs/?id=13772",
    "created_at": "2025-06-29T11:29:16.950263Z",
    "updated_at": "2025-06-29T11:29:16.950280Z",
    "entries": null,
    "keywords": null,
    "mark_as_removed": false,
    "removed_since": null,
    "guide": {
      "en": [
        "Gets the __name__ of a created with JobsReborn job."
      ],
      "ko": [
        "[JOBSSK] 한국어 가이드 번역 대기 중"
      ]
    }
  },
  "syntax_13767": {
    "id": 13767,
    "creator": "tgbhy",
    "title": "On Job Leave",
    "description": "Called when a player leaves a __JobsReborn__ job.",
    "syntax_pattern": "[on] player leave [(a|the)] job [[with name|named) ]%-string%]",
    "compatible_addon_version": "1.0.2",
    "compatible_minecraft_version": null,
    "syntax_type": "event",
    "required_plugins": [
      {
        "name": "JobsReborn",
        "link": ""
      }
    ],
    "addon": "JobsSK",
    "type_usage": null,
    "return_type": null,
    "event_values": "event-job, event-player",
    "event_cancellable": false,
    "link": "http://skripthub.net/docs/?id=13767",
    "created_at": "2025-06-29T11:15:51.652061Z",
    "updated_at": "2025-06-29T11:15:51.652078Z",
    "entries": null,
    "keywords": null,
    "mark_as_removed": false,
    "removed_since": null,
    "guide": {
      "en": [
        "Called when a player leaves a __JobsReborn__ job."
      ],
      "ko": [
        "[JOBSSK] 한국어 가이드 번역 대기 중"
      ]
    }
  }
}