{
  "syntax_13716": {
    "id": 13716,
    "type": "effect",
    "patterns": [],
    "added": "2.0",
    "guide": {
      "en": [
        "Binds a preset's abilities to a player.",
        "Can bind either player-specific presets or external presets.",
        "The abilities will be bound to the player's hotbar in the order they were added to the preset."
      ],
      "ko": [
        "[skript-pk] 한국어 가이드팩 준비 중"
      ]
    }
  },
  "syntax_13717": {
    "id": 13717,
    "type": "effect",
    "patterns": [],
    "added": "2.0",
    "guide": {
      "en": [
        "Assigns a ProjectKorra bending ability to a specific hotbar slot (1-9) for a player. If no slot is specified, it uses the player's currently selected hotbar slot."
      ],
      "ko": [
        "[skript-pk] 한국어 가이드팩 준비 중"
      ]
    }
  },
  "syntax_13718": {
    "id": 13718,
    "type": "effect",
    "patterns": [],
    "added": "2.0",
    "guide": {
      "en": [
        "Removes any bending ability bound to a specified hotbar slot. If no slot number is given, clears the ability from the player's currently selected slot. Use this to remove unwanted abilities from a player's hotbar."
      ],
      "ko": [
        "[skript-pk] 한국어 가이드팩 준비 중"
      ]
    }
  },
  "syntax_13719": {
    "id": 13719,
    "type": "effect",
    "patterns": [],
    "added": "2.0",
    "guide": {
      "en": [
        "Creates a new preset with optional abilities.",
        "Can create either a player-specific preset or an external preset.",
        "If a preset with the same name exists, it will be overwritten.",
        "External presets are available to all players."
      ],
      "ko": [
        "[skript-pk] 한국어 가이드팩 준비 중"
      ]
    }
  },
  "syntax_13720": {
    "id": 13720,
    "type": "effect",
    "patterns": [],
    "added": "2.0",
    "guide": {
      "en": [
        "Deletes a preset from a player or removes an external preset.",
        "Player presets are only deleted for that specific player.",
        "External presets are completely removed from the server."
      ],
      "ko": [
        "[skript-pk] 한국어 가이드팩 준비 중"
      ]
    }
  },
  "syntax_13721": {
    "id": 13721,
    "type": "effect",
    "patterns": [],
    "added": "2.0",
    "guide": {
      "en": [
        "Enables or disables all bending abilities for a player. When disabled, the player cannot use any bending abilities until re-enabled. Can toggle between states or set to a specific state."
      ],
      "ko": [
        "[skript-pk] 한국어 가이드팩 준비 중"
      ]
    }
  },
  "syntax_13722": {
    "id": 13722,
    "type": "expression",
    "patterns": [],
    "added": "2.0",
    "guide": {
      "en": [
        "Checks if a player's bending is enabled or disabled.",
        "Returns true if bending is enabled, false if disabled."
      ],
      "ko": [
        "[skript-pk] 한국어 가이드팩 준비 중"
      ]
    }
  },
  "syntax_13723": {
    "id": 13723,
    "type": "expression",
    "patterns": [],
    "added": "2.0",
    "guide": {
      "en": [
        "Returns the player's currently bound ability or the ability bound to a specific slot.",
        "If no slot is specified, returns the ability from the current active slot.",
        "Returns nothing if the slot is empty or invalid."
      ],
      "ko": [
        "[skript-pk] 한국어 가이드팩 준비 중"
      ]
    }
  },
  "syntax_13724": {
    "id": 13724,
    "type": "expression",
    "patterns": [],
    "added": "2.0",
    "guide": {
      "en": [
        "Returns a list of all preset names. Can return player-specific presets, external (global) presets, or both."
      ],
      "ko": [
        "[skript-pk] 한국어 가이드팩 준비 중"
      ]
    }
  },
  "syntax_13725": {
    "id": 13725,
    "type": "expression",
    "patterns": [],
    "added": "2.0",
    "guide": {
      "en": [
        "Returns a list of all abilities currently bound to a player's slots (1-9). Empty slots will return an empty string. The returned list is always 9 elements long, representing each slot."
      ],
      "ko": [
        "[skript-pk] 한국어 가이드팩 준비 중"
      ]
    }
  },
  "syntax_13726": {
    "id": 13726,
    "type": "expression",
    "patterns": [],
    "added": "2.0",
    "guide": {
      "en": [
        "Returns the element type (Water, Earth, Fire, Air, Chi, or sub-elements) of a specified ProjectKorra ability. Returns nothing if the ability doesn't exist."
      ],
      "ko": [
        "[skript-pk] 한국어 가이드팩 준비 중"
      ]
    }
  },
  "syntax_13727": {
    "id": 13727,
    "type": "expression",
    "patterns": [],
    "added": "2.0",
    "guide": {
      "en": [
        "Gets all abilities from a player's preset or an external preset.",
        "Returns a list of ability names stored in the preset."
      ],
      "ko": [
        "[skript-pk] 한국어 가이드팩 준비 중"
      ]
    }
  },
  "syntax_13715": {
    "id": 13715,
    "type": "condition",
    "patterns": [],
    "added": "2.0",
    "guide": {
      "en": [
        "Checks if a bending preset configuration exists. Can verify both player-specific presets and server-wide (external) presets."
      ],
      "ko": [
        "[skript-pk] 한국어 가이드팩 준비 중"
      ]
    }
  },
  "syntax_14240": {
    "id": 14240,
    "type": "condition",
    "patterns": [],
    "added": "2.0",
    "guide": {
      "en": [
        "Checks whether a location is occupied by a ProjectKorra TempBlock."
      ],
      "ko": [
        "[skript-pk] 한국어 가이드팩 준비 중"
      ]
    }
  },
  "syntax_14241": {
    "id": 14241,
    "type": "effect",
    "patterns": [],
    "added": "2.0",
    "guide": {
      "en": [
        "Creates a ProjectKorra TempBlock at the specified location, optionally reverting after a duration."
      ],
      "ko": [
        "[skript-pk] 한국어 가이드팩 준비 중"
      ]
    }
  },
  "syntax_14242": {
    "id": 14242,
    "type": "effect",
    "patterns": [],
    "added": "2.0",
    "guide": {
      "en": [
        "Reverts a ProjectKorra TempBlock at a location, optionally specifying the default material."
      ],
      "ko": [
        "[skript-pk] 한국어 가이드팩 준비 중"
      ]
    }
  },
  "syntax_14246": {
    "id": 14246,
    "type": "expression",
    "patterns": [],
    "added": "2.0",
    "guide": {
      "en": [
        "Returns the remaining duration of a ProjectKorra cooldown for a player as a timespan. Returns zero when the cooldown is not active."
      ],
      "ko": [
        "[skript-pk] 한국어 가이드팩 준비 중"
      ]
    }
  },
  "syntax_14244": {
    "id": 14244,
    "type": "effect",
    "patterns": [],
    "added": "2.0",
    "guide": {
      "en": [
        "Launches a registered ProjectKorra ability defined through this addon for a specific player."
      ],
      "ko": [
        "[skript-pk] 한국어 가이드팩 준비 중"
      ]
    }
  },
  "syntax_14247": {
    "id": 14247,
    "type": "expression",
    "patterns": [],
    "added": "2.0",
    "guide": {
      "en": [
        "Lists active ProjectKorra cooldowns for a player in the same order as /bending cooldown view."
      ],
      "ko": [
        "[skript-pk] 한국어 가이드팩 준비 중"
      ]
    }
  },
  "syntax_14243": {
    "id": 14243,
    "type": "effect",
    "patterns": [],
    "added": "2.0",
    "guide": {
      "en": [
        "Sets the anchor location for a running ability instance generated through this addon, allowing you to track it independently from the player."
      ],
      "ko": [
        "[skript-pk] 한국어 가이드팩 준비 중"
      ]
    }
  },
  "syntax_14250": {
    "id": 14250,
    "type": "type",
    "patterns": [],
    "added": "2.0",
    "guide": {
      "en": [
        "[skript-pk] No official English guide provided."
      ],
      "ko": [
        "[skript-pk] 한국어 가이드팩 준비 중"
      ]
    }
  },
  "syntax_14251": {
    "id": 14251,
    "type": "structure",
    "patterns": [],
    "added": "2.0",
    "guide": {
      "en": [
        "Defines a ProjectKorra ability implemented in Skript."
      ],
      "ko": [
        "[skript-pk] 한국어 가이드팩 준비 중"
      ]
    }
  },
  "syntax_14252": {
    "id": 14252,
    "type": "effect",
    "patterns": [],
    "added": "2.0",
    "guide": {
      "en": [
        "Clears a ProjectKorra cooldown for a player, or removes every active cooldown when using the \"all\" variant."
      ],
      "ko": [
        "[skript-pk] 한국어 가이드팩 준비 중"
      ]
    }
  },
  "syntax_14253": {
    "id": 14253,
    "type": "effect",
    "patterns": [],
    "added": "2.0",
    "guide": {
      "en": [
        "Sets a ProjectKorra cooldown for a player. Using a non-positive duration removes the cooldown instead."
      ],
      "ko": [
        "[skript-pk] 한국어 가이드팩 준비 중"
      ]
    }
  },
  "syntax_14248": {
    "id": 14248,
    "type": "expression",
    "patterns": [],
    "added": "2.0",
    "guide": {
      "en": [
        "Returns recent bendable block sources for a player's element using ProjectKorra's BlockSource logic."
      ],
      "ko": [
        "[skript-pk] 한국어 가이드팩 준비 중"
      ]
    }
  },
  "syntax_14249": {
    "id": 14249,
    "type": "type",
    "patterns": [],
    "added": "2.0",
    "guide": {
      "en": [
        "[skript-pk] No official English guide provided."
      ],
      "ko": [
        "[skript-pk] 한국어 가이드팩 준비 중"
      ]
    }
  },
  "syntax_14245": {
    "id": 14245,
    "type": "effect",
    "patterns": [],
    "added": "2.0",
    "guide": {
      "en": [
        "Ends a running ProjectKorra ability generated through this addon. When used without an argument inside start/progress/remove sections, it stops the active ability instance."
      ],
      "ko": [
        "[skript-pk] 한국어 가이드팩 준비 중"
      ]
    }
  }
}